<annotation>
	<folder>Images</folder>
	<filename>sauce mafe.png</filename>
	<path>/home/elvira/Images/sauce mafe.png</path>
	<source>
		<database>Unknown</database>
	</source>
	<size>
		<width>742</width>
		<height>559</height>
		<depth>3</depth>
	</size>
	<segmented>0</segmented>
	<object>
		<name>celeri</name>
		<pose>Unspecified</pose>
		<truncated>0</truncated>
		<difficult>0</difficult>
		<bndbox>
			<xmin>278</xmin>
			<ymin>227</ymin>
			<xmax>446</xmax>
			<ymax>343</ymax>
		</bndbox>
	</object>
	<object>
		<name>poulet</name>
		<pose>Unspecified</pose>
		<truncated>0</truncated>
		<difficult>0</difficult>
		<bndbox>
			<xmin>481</xmin>
			<ymin>186</ymin>
			<xmax>587</xmax>
			<ymax>290</ymax>
		</bndbox>
	</object>
	<object>
		<name>sauce mafe</name>
		<pose>Unspecified</pose>
		<truncated>0</truncated>
		<difficult>0</difficult>
		<bndbox>
			<xmin>294</xmin>
			<ymin>47</ymin>
			<xmax>458</xmax>
			<ymax>119</ymax>
		</bndbox>
	</object>
</annotation>
